provolone/__init__.py
provolone/cli.py
provolone/config.py
provolone/snapshots.py
provolone/datasets/__init__.py
provolone/datasets/base.py
provolone/datasets/crsp/__init__.py
provolone/datasets/crsp/loader.py
provolone/datasets/example/__init__.py
provolone/datasets/example/loader.py
provolone/utils/file_meta.py
provolone/utils/hash.py
provolone/utils/index_meta.py
provolone/utils/source.py
provolone-0.0.1.dist-info/licenses/LICENSE
provolone-0.0.1.dist-info/METADATA
provolone-0.0.1.dist-info/WHEEL
provolone-0.0.1.dist-info/entry_points.txt
provolone-0.0.1.dist-info/top_level.txt
provolone-0.0.1.dist-info/RECORD
