Metadata-Version: 2.4
Name: provolone
Version: 0.0.1
Summary: Package to create and track provenance metadata for datasets
Author: Daniel Greenwald
License: MIT
Project-URL: Homepage, https://github.com/dgreenwald/provolone
Project-URL: Repository, https://github.com/dgreenwald/provolone
Project-URL: Issues, https://github.com/dgreenwald/provolone/issues
Keywords: data,economics,datasets,pandas,snapshots
Classifier: Development Status :: 3 - Alpha
Classifier: Intended Audience :: Science/Research
Classifier: License :: OSI Approved :: MIT License
Classifier: Programming Language :: Python :: 3
Classifier: Programming Language :: Python :: 3.10
Classifier: Programming Language :: Python :: 3.11
Classifier: Programming Language :: Python :: 3.12
Classifier: Topic :: Scientific/Engineering
Requires-Python: >=3.10
License-File: LICENSE
Requires-Dist: pandas>=2.1
Requires-Dist: pyarrow>=17
Requires-Dist: pydantic>=2.8
Requires-Dist: pydantic-settings>=2.3
Requires-Dist: python-dateutil>=2.9
Requires-Dist: typer>=0.9.0
Provides-Extra: dev
Requires-Dist: pytest>=8.2; extra == "dev"
Requires-Dist: ruff>=0.6; extra == "dev"
Requires-Dist: black>=24.8; extra == "dev"
Requires-Dist: mypy>=1.11; extra == "dev"
Dynamic: license-file
